a2rpc/__main__.py
a2rpc/cliskel.py
a2rpc-0.0.3.dist-info/licenses/LICENSE
a2rpc-0.0.3.dist-info/METADATA
a2rpc-0.0.3.dist-info/WHEEL
a2rpc-0.0.3.dist-info/entry_points.txt
a2rpc-0.0.3.dist-info/top_level.txt
a2rpc-0.0.3.dist-info/RECORD
