Metadata-Version: 2.4
Name: a2rpc
Version: 0.0.3
Summary: A CLI tool to interact with aria2c's RPC interface
Author: Jet-Logic
License:                     GNU GENERAL PUBLIC LICENSE
Project-URL: Homepage, https://github.com/jet-logic/a2rpc
Project-URL: Documentation, https://github.com/jet-logic/a2rpc#readme
Project-URL: BugTracker, https://github.com/jet-logic/a2rpc/issues
Project-URL: Changelog, https://github.com/jet-logic/a2rpc/releases
Keywords: aria2,rpc,cli,download,torrent,magnet
Classifier: Development Status :: 4 - Beta
Classifier: Environment :: Console
Classifier: Intended Audience :: End Users/Desktop
Classifier: Intended Audience :: System Administrators
Classifier: Operating System :: OS Independent
Classifier: Programming Language :: Python :: 3
Classifier: Topic :: Internet :: WWW/HTTP
Classifier: Topic :: Utilities
License-File: LICENSE
Requires-Dist: requests
Requires-Dist: pyyaml
Provides-Extra: dev
Requires-Dist: black>=23.0; extra == "dev"
Requires-Dist: flake8>=6.0; extra == "dev"
Requires-Dist: mypy>=1.0; extra == "dev"
Requires-Dist: pytest>=7.0; extra == "dev"
Requires-Dist: types-requests>=2.0; extra == "dev"
Requires-Dist: types-PyYAML>=6.0; extra == "dev"
Provides-Extra: test
Requires-Dist: pytest>=7.0; extra == "test"
Requires-Dist: pytest-cov>=4.0; extra == "test"
Dynamic: license-file
